odoo8_addon_product_stock_state-8.0.1.0.0.99.dev4-py3.8-nspkg.pth
odoo_addons/product_stock_state/README.rst
odoo_addons/product_stock_state/__init__.py
odoo_addons/product_stock_state/__openerp__.py
odoo_addons/product_stock_state/models/__init__.py
odoo_addons/product_stock_state/models/product.py
odoo_addons/product_stock_state/views/product_view.xml
odoo8_addon_product_stock_state-8.0.1.0.0.99.dev4.dist-info/METADATA
odoo8_addon_product_stock_state-8.0.1.0.0.99.dev4.dist-info/WHEEL
odoo8_addon_product_stock_state-8.0.1.0.0.99.dev4.dist-info/namespace_packages.txt
odoo8_addon_product_stock_state-8.0.1.0.0.99.dev4.dist-info/top_level.txt
odoo8_addon_product_stock_state-8.0.1.0.0.99.dev4.dist-info/RECORD
